Workbook

Sheet Attendance_Sheet
E7: Month | F7: Year | G7: ="Fully Automatic Attendance Sheet - "&E8&" "&F8 -> Fully Automatic Attendance Sheet - June 2026
E8: June | F8: 2026
E9: =DATEVALUE("1"&E8&F8) -> 46174 | F9: =EOMONTH(E9,0) -> 46203
E10: EMP_ID | F10: EMP_Name | G10: =E9 -> 46174 | H10: =IF(G10<$F$9,G10+1,"") -> 46175 | I10: =IF(H10<$F$9,H10+1,"") -> 46176 | J10: =IF(I10<$F$9,I10+1,"") -> 46177 | K10: =IF(J10<$F$9,J10+1,"") -> 46178 | L10: =IF(K10<$F$9,K10+1,"") -> 46179 | M10: =IF(L10<$F$9,L10+1,"") -> 46180 | N10: =IF(M10<$F$9,M10+1,"") -> 46181 | O10: =IF(N10<$F$9,N10+1,"") -> 46182 | ... AK10: =IF(AJ10<$F$9,AJ10+1,"") | AL10: Total Days | AM10: Present | AN10: Holiday | AO10: Week Off | AP10: Absent
G11: =TEXT(G10,"ddd") -> Mon | H11: =TEXT(H10,"ddd") -> Tue | I11: =TEXT(I10,"ddd") -> Wed | J11: =TEXT(J10,"ddd") -> Thu | K11: =TEXT(K10,"ddd") -> Fri | L11: =TEXT(L10,"ddd") -> Sat | M11: =TEXT(M10,"ddd") -> Sun | N11: =TEXT(N10,"ddd") -> Mon | ... AK11: =TEXT(AK10,"ddd")
E13: EMP001 | F13: Buckminster | G13: H | H13: P | I13: P | J13: P | K13: P | L13: P | N13: P | AL13: =COUNT($G$10:$AK$10) -> 30 | AM13: =COUNTIF($G13:$AK13,"P") -> 6 | AN13: =COUNTIF($G13:$AK13,"H") -> 1 | AO13: =COUNTIF(G$11:AK$12,"Sun") -> 4 | AP13: =COUNTIF($G13:$AK13,"A") -> 0
E14: EMP002 | F14: Tesla | G14: H | H14: A | I14: P | J14: P | K14: P | L14: P | N14: P | AL14: =COUNT($G$10:$AK$10) -> 30 | AM14: =COUNTIF($G14:$AK14,"P") -> 5 | AN14: =COUNTIF($G14:$AK14,"H") -> 1 | AO14: =COUNTIF(G$11:AK$12,"Sun") -> 4 | AP14: =COUNTIF($G14:$AK14,"A") -> 1
E15: EMP003 | F15: Ada | G15: H | H15: P | I15: P | J15: P | K15: P | L15: P | N15: P | AL15: =COUNT($G$10:$AK$10) -> 30 | AM15: =COUNTIF($G15:$AK15,"P") -> 6 | AN15: =COUNTIF($G15:$AK15,"H") -> 1 | AO15: =COUNTIF(G$11:AK$12,"Sun") -> 4 | AP15: =COUNTIF($G15:$AK15,"A") -> 0
E16: EMP004 | F16: Galileo | G16: H | H16: P | I16: P | J16: P | K16: P | L16: P | N16: A | AL16: =COUNT($G$10:$AK$10) -> 30 | AM16: =COUNTIF($G16:$AK16,"P") -> 5 | AN16: =COUNTIF($G16:$AK16,"H") -> 1 | AO16: =COUNTIF(G$11:AK$12,"Sun") -> 4 | AP16: =COUNTIF($G16:$AK16,"A") -> 1
E17: EMP005 | F17: Atlas | G17: H | H17: P | I17: P | J17: P | K17: P | L17: P | N17: A | AL17: =COUNT($G$10:$AK$10) -> 30 | AM17: =COUNTIF($G17:$AK17,"P") -> 5 | AN17: =COUNTIF($G17:$AK17,"H") -> 1 | AO17: =COUNTIF(G$11:AK$12,"Sun") -> 4 | AP17: =COUNTIF($G17:$AK17,"A") -> 1
E18: EMP006 | F18: Gaia | G18: H | H18: P | I18: P | J18: P | K18: P | L18: P | N18: P | AL18: =COUNT($G$10:$AK$10) -> 30 | AM18: =COUNTIF($G18:$AK18,"P") -> 6 | AN18: =COUNTIF($G18:$AK18,"H") -> 1 | AO18: =COUNTIF(G$11:AK$12,"Sun") -> 4 | AP18: =COUNTIF($G18:$AK18,"A") -> 0
E19: EMP007 | F19: Apollo | G19: H | H19: P | I19: P | J19: A | K19: P | L19: P | N19: P | AL19: =COUNT($G$10:$AK$10) -> 30 | AM19: =COUNTIF($G19:$AK19,"P") -> 5 | AN19: =COUNTIF($G19:$AK19,"H") -> 1 | AO19: =COUNTIF(G$11:AK$12,"Sun") -> 4 | AP19: =COUNTIF($G19:$AK19,"A") -> 1
E20: EMP008 | F20: Athena | G20: H | H20: P | I20: P | J20: P | K20: P | L20: P | N20: P | AL20: =COUNT($G$10:$AK$10) -> 30 | AM20: =COUNTIF($G20:$AK20,"P") -> 6 | AN20: =COUNTIF($G20:$AK20,"H") -> 1 | AO20: =COUNTIF(G$11:AK$12,"Sun") -> 4 | AP20: =COUNTIF($G20:$AK20,"A") -> 0
E21: EMP009 | F21: Da Vinci | G21: H | H21: P | I21: P | J21: P | K21: P | L21: P | N21: P | AL21: =COUNT($G$10:$AK$10) -> 30 | AM21: =COUNTIF($G21:$AK21,"P") -> 6 | AN21: =COUNTIF($G21:$AK21,"H") -> 1 | AO21: =COUNTIF(G$11:AK$12,"Sun") -> 4 | AP21: =COUNTIF($G21:$AK21,"A") -> 0
E22: EMP010 | F22: Cousteau | G22: H | H22: P | I22: A | J22: P | K22: P | L22: P | N22: P | AL22: =COUNT($G$10:$AK$10) -> 30 | AM22: =COUNTIF($G22:$AK22,"P") -> 5 | AN22: =COUNTIF($G22:$AK22,"H") -> 1 | AO22: =COUNTIF(G$11:AK$12,"Sun") -> 4 | AP22: =COUNTIF($G22:$AK22,"A") -> 1
E23: EMP011 | F23: Amundsen | G23: H | H23: P | I23: P | J23: P | K23: P | L23: P | N23: P | AL23: =COUNT($G$10:$AK$10) -> 30 | AM23: =COUNTIF($G23:$AK23,"P") -> 6 | AN23: =COUNTIF($G23:$AK23,"H") -> 1 | AO23: =COUNTIF(G$11:AK$12,"Sun") -> 4 | AP23: =COUNTIF($G23:$AK23,"A") -> 0
E24: EMP012 | F24: Sagan | G24: H | H24: P | I24: P | J24: P | K24: P | L24: P | N24: P | AL24: =COUNT($G$10:$AK$10) -> 30 | AM24: =COUNTIF($G24:$AK24,"P") -> 6 | AN24: =COUNTIF($G24:$AK24,"H") -> 1 | AO24: =COUNTIF(G$11:AK$12,"Sun") -> 4 | AP24: =COUNTIF($G24:$AK24,"A") -> 0
E25: EMP013 | F25: Orion | G25: H | H25: P | I25: P | J25: P | K25: P | L25: P | N25: P | AL25: =COUNT($G$10:$AK$10) -> 30 | AM25: =COUNTIF($G25:$AK25,"P") -> 6 | AN25: =COUNTIF($G25:$AK25,"H") -> 1 | AO25: =COUNTIF(G$11:AK$12,"Sun") -> 4 | AP25: =COUNTIF($G25:$AK25,"A") -> 0
A30: January
A31: February
A32: March
A33: April
A34: May
A35: June
A36: July
A37: August
A38: September
A39: October
A40: November
A41: December

Sheet Salary_Sheet
C4: ="Fully Automatic Salary Sheet - "&Attendance_Sheet!E8&" "&Attendance_Sheet!F8&"" -> Fully Automatic Salary Sheet - June 2026
C7: EMP_ID | D7: EMP_Name | E7: Designation | F7: Basic Salary | G7: Total Days | H7: Attendance (Working Days) | I7: Per day Salary | J7: Salary (Based on Attendance) | K7: DA (12%) | L7: City | M7: HRA | N7: TA | O7: OT In Hrs | P7: Overtime Pay | Q7: Gross Salary | R7: PF (12%) | S7: ESI (0.75%) | T7: Net Salary
C8: =Attendance_Sheet!E13 -> EMP001 | D8: =Attendance_Sheet!F13 -> Buckminster | E8: Manager | F8: 95000 | G8: =Attendance_Sheet!AL13 -> 30 | H8: =SUM(Attendance_Sheet!AM13:AO13) -> 11 | I8: =F8/G8 -> 3166.6667 | J8: =H8*I8 -> 34833.333 | K8: =F8*12% -> 11400 | L8: Metro | M8: =IF(L8="Metro",F8*50%,F8*40%) -> 47500 | N8: 1000 | O8: 5 | P8: =I8/9*O8 -> 1759.2593 | Q8: =J8+K8+M8+N8 -> 94733.333 | R8: =F8*12% -> 11400 | S8: =IF(Q8<=21000,Q8*0.75%,"0") -> 0 | T8: =IF(ISNUMBER(S8),Q8+R8+S8,Q8+R8) -> 106133.33
C9: =Attendance_Sheet!E14 -> EMP002 | D9: =Attendance_Sheet!F14 -> Tesla | E9: Team Lead | F9: 55000 | G9: =Attendance_Sheet!AL14 -> 30 | H9: =SUM(Attendance_Sheet!AM14:AO14) -> 10 | I9: =F9/G9 -> 1833.3333 | J9: =H9*I9 -> 18333.333 | K9: =F9*12% -> 6600 | L9: Metro | M9: =IF(L9="Metro",F9*50%,F9*40%) -> 27500 | N9: 2000 | O9: 6 | P9: =I9/9*O9 -> 1222.2222 | Q9: =J9+K9+M9+N9 -> 54433.333 | R9: =F9*12% -> 6600 | S9: =IF(Q9<=21000,Q9*0.75%,"0") -> 0 | T9: =IF(ISNUMBER(S9),Q9+R9+S9,Q9+R9) -> 61033.333
C10: =Attendance_Sheet!E15 -> EMP003 | D10: =Attendance_Sheet!F15 -> Ada | E10: Team Lead | F10: 55000 | G10: =Attendance_Sheet!AL15 -> 30 | H10: =SUM(Attendance_Sheet!AM15:AO15) -> 11 | I10: =F10/G10 -> 1833.3333 | J10: =H10*I10 -> 20166.667 | K10: =F10*12% -> 6600 | L10: Metro | M10: =IF(L10="Metro",F10*50%,F10*40%) -> 27500 | N10: 1000 | O10: 7 | P10: =I10/9*O10 -> 1425.9259 | Q10: =J10+K10+M10+N10 -> 55266.667 | R10: =F10*12% -> 6600 | S10: =IF(Q10<=21000,Q10*0.75%,"0") -> 0 | T10: =IF(ISNUMBER(S10),Q10+R10+S10,Q10+R10) -> 61866.667
C11: =Attendance_Sheet!E16 -> EMP004 | D11: =Attendance_Sheet!F16 -> Galileo | E11: MIS | F11: 45000 | G11: =Attendance_Sheet!AL16 -> 30 | H11: =SUM(Attendance_Sheet!AM16:AO16) -> 10 | I11: =F11/G11 -> 1500 | J11: =H11*I11 -> 15000 | K11: =F11*12% -> 5400 | L11: Non-Metro | M11: =IF(L11="Metro",F11*50%,F11*40%) -> 18000 | N11: 2000 | O11: 8 | P11: =I11/9*O11 -> 1333.3333 | Q11: =J11+K11+M11+N11 -> 40400 | R11: =F11*12% -> 5400 | S11: =IF(Q11<=21000,Q11*0.75%,"0") -> 0 | T11: =IF(ISNUMBER(S11),Q11+R11+S11,Q11+R11) -> 45800
C12: =Attendance_Sheet!E17 -> EMP005 | D12: =Attendance_Sheet!F17 -> Atlas | E12: WFM | F12: 35000 | G12: =Attendance_Sheet!AL17 -> 30 | H12: =SUM(Attendance_Sheet!AM17:AO17) -> 10 | I12: =F12/G12 -> 1166.6667 | J12: =H12*I12 -> 11666.667 | K12: =F12*12% -> 4200 | L12: Non-Metro | M12: =IF(L12="Metro",F12*50%,F12*40%) -> 14000 | N12: 1000 | O12: 10 | P12: =I12/9*O12 -> 1296.2963 | Q12: =J12+K12+M12+N12 -> 30866.667 | R12: =F12*12% -> 4200 | S12: =IF(Q12<=21000,Q12*0.75%,"0") -> 0 | T12: =IF(ISNUMBER(S12),Q12+R12+S12,Q12+R12) -> 35066.667
C13: =Attendance_Sheet!E18 -> EMP006 | D13: =Attendance_Sheet!F18 -> Gaia | E13: Executive | F13: 15000 | G13: =Attendance_Sheet!AL18 -> 30 | H13: =SUM(Attendance_Sheet!AM18:AO18) -> 11 | I13: =F13/G13 -> 500 | J13: =H13*I13 -> 5500 | K13: =F13*12% -> 1800 | L13: Metro | M13: =IF(L13="Metro",F13*50%,F13*40%) -> 7500 | N13: 1000 | O13: 8 | P13: =I13/9*O13 -> 444.44444 | Q13: =J13+K13+M13+N13 -> 15800 | R13: =F13*12% -> 1800 | S13: =IF(Q13<=21000,Q13*0.75%,"0") -> 118.5 | T13: =IF(ISNUMBER(S13),Q13+R13+S13,Q13+R13) -> 17718.5
C14: =Attendance_Sheet!E19 -> EMP007 | D14: =Attendance_Sheet!F19 -> Apollo | E14: Executive | F14: 15000 | G14: =Attendance_Sheet!AL19 -> 30 | H14: =SUM(Attendance_Sheet!AM19:AO19) -> 10 | I14: =F14/G14 -> 500 | J14: =H14*I14 -> 5000 | K14: =F14*12% -> 1800 | L14: Metro | M14: =IF(L14="Metro",F14*50%,F14*40%) -> 7500 | N14: 1000 | O14: 3 | P14: =I14/9*O14 -> 166.66667 | Q14: =J14+K14+M14+N14 -> 15300 | R14: =F14*12% -> 1800 | S14: =IF(Q14<=21000,Q14*0.75%,"0") -> 114.75 | T14: =IF(ISNUMBER(S14),Q14+R14+S14,Q14+R14) -> 17214.75
C15: =Attendance_Sheet!E20 -> EMP008 | D15: =Attendance_Sheet!F20 -> Athena | E15: Executive | F15: 15000 | G15: =Attendance_Sheet!AL20 -> 30 | H15: =SUM(Attendance_Sheet!AM20:AO20) -> 11 | I15: =F15/G15 -> 500 | J15: =H15*I15 -> 5500 | K15: =F15*12% -> 1800 | L15: Non-Metro | M15: =IF(L15="Metro",F15*50%,F15*40%) -> 6000 | N15: 3000 | O15: 4 | P15: =I15/9*O15 -> 222.22222 | Q15: =J15+K15+M15+N15 -> 16300 | R15: =F15*12% -> 1800 | S15: =IF(Q15<=21000,Q15*0.75%,"0") -> 122.25 | T15: =IF(ISNUMBER(S15),Q15+R15+S15,Q15+R15) -> 18222.25
C16: =Attendance_Sheet!E21 -> EMP009 | D16: =Attendance_Sheet!F21 -> Da Vinci | E16: Executive | F16: 15000 | G16: =Attendance_Sheet!AL21 -> 30 | H16: =SUM(Attendance_Sheet!AM21:AO21) -> 11 | I16: =F16/G16 -> 500 | J16: =H16*I16 -> 5500 | K16: =F16*12% -> 1800 | L16: Metro | M16: =IF(L16="Metro",F16*50%,F16*40%) -> 7500 | N16: 1000 | O16: 5 | P16: =I16/9*O16 -> 277.77778 | Q16: =J16+K16+M16+N16 -> 15800 | R16: =F16*12% -> 1800 | S16: =IF(Q16<=21000,Q16*0.75%,"0") -> 118.5 | T16: =IF(ISNUMBER(S16),Q16+R16+S16,Q16+R16) -> 17718.5
C17: =Attendance_Sheet!E22 -> EMP010 | D17: =Attendance_Sheet!F22 -> Cousteau | E17: Sr.Executive | F17: 25000 | G17: =Attendance_Sheet!AL22 -> 30 | H17: =SUM(Attendance_Sheet!AM22:AO22) -> 10 | I17: =F17/G17 -> 833.33333 | J17: =H17*I17 -> 8333.3333 | K17: =F17*12% -> 3000 | L17: Metro | M17: =IF(L17="Metro",F17*50%,F17*40%) -> 12500 | N17: 1000 | O17: 6 | P17: =I17/9*O17 -> 555.55556 | Q17: =J17+K17+M17+N17 -> 24833.333 | R17: =F17*12% -> 3000 | S17: =IF(Q17<=21000,Q17*0.75%,"0") -> 0 | T17: =IF(ISNUMBER(S17),Q17+R17+S17,Q17+R17) -> 27833.333
C18: =Attendance_Sheet!E23 -> EMP011 | D18: =Attendance_Sheet!F23 -> Amundsen | E18: Sr.Executive | F18: 25000 | G18: =Attendance_Sheet!AL23 -> 30 | H18: =SUM(Attendance_Sheet!AM23:AO23) -> 11 | I18: =F18/G18 -> 833.33333 | J18: =H18*I18 -> 9166.6667 | K18: =F18*12% -> 3000 | L18: Metro | M18: =IF(L18="Metro",F18*50%,F18*40%) -> 12500 | N18: 1000 | O18: 7 | P18: =I18/9*O18 -> 648.14815 | Q18: =J18+K18+M18+N18 -> 25666.667 | R18: =F18*12% -> 3000 | S18: =IF(Q18<=21000,Q18*0.75%,"0") -> 0 | T18: =IF(ISNUMBER(S18),Q18+R18+S18,Q18+R18) -> 28666.667
C19: =Attendance_Sheet!E24 -> EMP012 | D19: =Attendance_Sheet!F24 -> Sagan | E19: Quality | F19: 20000 | G19: =Attendance_Sheet!AL24 -> 30 | H19: =SUM(Attendance_Sheet!AM24:AO24) -> 11 | I19: =F19/G19 -> 666.66667 | J19: =H19*I19 -> 7333.3333 | K19: =F19*12% -> 2400 | L19: Non-Metro | M19: =IF(L19="Metro",F19*50%,F19*40%) -> 8000 | N19: 3000 | O19: 5 | P19: =I19/9*O19 -> 370.37037 | Q19: =J19+K19+M19+N19 -> 20733.333 | R19: =F19*12% -> 2400 | S19: =IF(Q19<=21000,Q19*0.75%,"0") -> 155.5 | T19: =IF(ISNUMBER(S19),Q19+R19+S19,Q19+R19) -> 23288.833
C20: =Attendance_Sheet!E25 -> EMP013 | D20: =Attendance_Sheet!F25 -> Orion | E20: Trainer | F20: 20000 | G20: =Attendance_Sheet!AL25 -> 30 | H20: =SUM(Attendance_Sheet!AM25:AO25) -> 11 | I20: =F20/G20 -> 666.66667 | J20: =H20*I20 -> 7333.3333 | K20: =F20*12% -> 2400 | L20: Metro | M20: =IF(L20="Metro",F20*50%,F20*40%) -> 10000 | N20: 3000 | O20: 5 | P20: =I20/9*O20 -> 370.37037 | Q20: =J20+K20+M20+N20 -> 22733.333 | R20: =F20*12% -> 2400 | S20: =IF(Q20<=21000,Q20*0.75%,"0") -> 0 | T20: =IF(ISNUMBER(S20),Q20+R20+S20,Q20+R20) -> 25133.333

Sheet Salary_Slip
E3: Github Services Private Limited
F4: Prepared By Rihanshu Bishwakarma
F5: ABC Colony, Sarovar Road , Kolkata - 870000
F6: ="Salary Slip For the Month Of - "&Attendance_Sheet!E8&" "&Attendance_Sheet!F8&"" -> Salary Slip For the Month Of - June 2026
F8: Employee Details | M8: Salary Details
G9: Emp_ID | J9: EMP001 | N9: Total Days | Q9: =VLOOKUP($J$9,Salary_Sheet!$C$7:$T$20,MATCH($N$9,Salary_Sheet!$C$7:$T$7,0),0) -> 30
G10: EMP_Name | J10: =VLOOKUP($J$9,Salary_Sheet!$C$7:$T$20,MATCH(Salary_Slip!$G$10,Salary_Sheet!$C$7:$T$7,0),0) -> Buckminster | N10: Attendance (Working Days) | Q10: =VLOOKUP($J$9,Salary_Sheet!$C$7:$T$20,MATCH($N$10,Salary_Sheet!$C$7:$T$7,0),0) -> 11
G11: Designation | J11: =VLOOKUP($J$9,Salary_Sheet!$C$7:$T$20,MATCH($G$11,Salary_Sheet!$C$7:$T$7,0),0) -> Manager | N11: Salary Slip Print Date | Q11: =TODAY() -> 46181
F13: Employee Details | G13: Basic Salary | M13: Employee Details | N13: =VLOOKUP($J$9,Salary_Sheet!$C$7:$T$20,MATCH(Salary_Slip!$G$13,Salary_Sheet!$C$7:$T$7,0),0) -> 95000
F15: Earnings | M15: Deductions
G16: Salary (Based on Attendance) | J16: =VLOOKUP($J$9,Salary_Sheet!$C$7:$T$20,MATCH($G$16,Salary_Sheet!$C$7:$T$7,0),0) -> 34833.333 | N16: PF (12%) | Q16: =VLOOKUP($J$9,Salary_Sheet!$C$7:$T$20,MATCH($N$16,Salary_Sheet!$C$7:$T$7,0),0) -> 11400
G17: DA (12%) | J17: =VLOOKUP($J$9,Salary_Sheet!$C$7:$T$20,MATCH($G$17,Salary_Sheet!$C$7:$T$7,0),0) -> 11400 | N17: ESI (0.75%) | Q17: =VLOOKUP($J$9,Salary_Sheet!$C$7:$T$20,MATCH($N$17,Salary_Sheet!$C$7:$T$7,0),0) -> 0
G18: HRA | J18: =VLOOKUP($J$9,Salary_Sheet!$C$7:$T$20,MATCH($G$18,Salary_Sheet!$C$7:$T$7,0),0) -> 47500 | N18: Loan | Q18: =IFERROR(VLOOKUP($J$9,Salary_Sheet!$C$7:$T$20,MATCH($N$18,Salary_Sheet!$C$7:$T$7,0),0),"0") -> 0
G19: TA | J19: =VLOOKUP($J$9,Salary_Sheet!$C$7:$T$20,MATCH($G$19,Salary_Sheet!$C$7:$T$7,0),0) -> 1000 | N19: Tax | Q19: =IFERROR(VLOOKUP($J$9,Salary_Sheet!$C$7:$T$20,MATCH($N$19,Salary_Sheet!$C$7:$T$7,0),0),"0") -> 0
G20: Overtime Pay | J20: =VLOOKUP($J$9,Salary_Sheet!$C$7:$T$20,MATCH($G$20,Salary_Sheet!$C$7:$T$7,0),0) -> 1759.2593
G21: Gross Salary | J21: =SUM(J16:L20) -> 96492.593 | N21: Gross Deduction | Q21: =SUM(Q16:S20) -> 11400
F23: Employee Details | G23: Net Salary | M23: Employee Details | N23: =J21-Q21 -> 85092.593
G25: Employee Signature | J25: _______________________________ | N25: Manager Signature | Q25: _______________________________
F27: This Is a Sample Salaty Slip Generated for Education Purpose
